{
  "schemaVersion": 1,
  "itemId": "base-ui/menu",
  "routePath": "/components/base-ui/menu",
  "title": "Menu",
  "description": "Foldkit-native Base UI Menu primitive preserving model-owned open, submenu, highlighted, checked, and radio state, popup/menu ARIA, local keyboard navigation, typeahead, disabled items, grouping, separators, arrows, deterministic placement attributes, and dismiss events.",
  "docsStatus": "missing",
  "markdownPath": null,
  "markdown": null,
  "headings": [],
  "installCommand": "bunx shadcn@latest add @foldkitcn/base-ui-menu",
  "localInstallPath": "src/registry/base-ui/menu",
  "defaultImportPath": "base-ui/menu",
  "sourceRoot": "registry-src/base-ui/menu",
  "installableSourcePaths": ["src/registry/base-ui/menu/index.ts"],
  "sourceFiles": [
    {
      "path": "src/registry/base-ui/menu/index.ts",
      "content": "import { Option, Predicate, Schema as S } from 'effect'\nimport type { Command } from 'foldkit'\nimport type { Attribute, Html, KeyboardModifiers } from 'foldkit/html'\nimport { html } from 'foldkit/html'\n\nimport * as Popover from '../popover'\n\n// MODEL\n\nexport const MenuSide = Popover.PopoverSide\nexport type MenuSide = Popover.PopoverSide\n\nexport const MenuAlign = Popover.PopoverAlign\nexport type MenuAlign = Popover.PopoverAlign\n\nexport const MenuTransitionStatus = Popover.PopoverTransitionStatus\nexport type MenuTransitionStatus = Popover.PopoverTransitionStatus\n\nexport const MenuItemKind = S.Union([\n  S.Literal('item'),\n  S.Literal('checkbox'),\n  S.Literal('radio'),\n  S.Literal('submenu-trigger'),\n])\nexport type MenuItemKind = typeof MenuItemKind.Type\n\nexport const MenuOpenChangeReason = S.Union([\n  S.Literal('trigger-press'),\n  S.Literal('item-press'),\n  S.Literal('outside-press'),\n  S.Literal('escape-key'),\n  S.Literal('keyboard-open'),\n  S.Literal('submenu-open'),\n  S.Literal('submenu-close'),\n  S.Literal('none'),\n])\nexport type MenuOpenChangeReason = typeof MenuOpenChangeReason.Type\n\nexport const MenuHighlightChangeReason = S.Union([\n  S.Literal('keyboard-navigation'),\n  S.Literal('typeahead'),\n  S.Literal('item-hover'),\n  S.Literal('none'),\n])\nexport type MenuHighlightChangeReason = typeof MenuHighlightChangeReason.Type\n\nexport const MenuOpenChange = S.Struct({\n  open: S.Boolean,\n  reason: MenuOpenChangeReason,\n  parentValue: S.optional(S.String),\n})\nexport type MenuOpenChange = typeof MenuOpenChange.Type\n\nexport const MenuHighlightChange = S.Struct({\n  value: S.String,\n  reason: MenuHighlightChangeReason,\n  focusSelector: S.optional(S.String),\n})\nexport type MenuHighlightChange = typeof MenuHighlightChange.Type\n\nexport const MenuItemPress = S.Struct({\n  value: S.String,\n  kind: MenuItemKind,\n})\nexport type MenuItemPress = typeof MenuItemPress.Type\n\nexport const MenuCheckedChange = S.Struct({\n  value: S.String,\n  checked: S.Boolean,\n})\nexport type MenuCheckedChange = typeof MenuCheckedChange.Type\n\nexport const MenuRadioValueChange = S.Struct({\n  groupValue: S.String,\n  value: S.String,\n})\nexport type MenuRadioValueChange = typeof MenuRadioValueChange.Type\n\nexport const MenuItemDescriptor = S.Struct({\n  id: S.optional(S.String),\n  value: S.String,\n  label: S.String,\n  textValue: S.optional(S.String),\n  kind: S.optional(MenuItemKind),\n  isDisabled: S.optional(S.Boolean),\n  isChecked: S.optional(S.Boolean),\n  radioGroupValue: S.optional(S.String),\n  parentValue: S.optional(S.String),\n})\nexport type MenuItemDescriptor = typeof MenuItemDescriptor.Type\n\nexport const MenuOptions = S.Struct({\n  id: S.String,\n  open: S.Boolean,\n  items: S.Array(MenuItemDescriptor),\n  highlightedValue: S.optional(S.String),\n  openSubmenuValues: S.optional(S.Array(S.String)),\n  forceMount: S.optional(S.Boolean),\n  transitionStatus: S.optional(MenuTransitionStatus),\n  isDisabled: S.optional(S.Boolean),\n  side: S.optional(MenuSide),\n  align: S.optional(MenuAlign),\n  sideOffset: S.optional(S.Number),\n  alignOffset: S.optional(S.Number),\n  collisionAvoidance: S.optional(S.Boolean),\n  collisionPadding: S.optional(S.Number),\n  triggerId: S.optional(S.String),\n  triggerSelector: S.optional(S.String),\n})\nexport type MenuOptions = typeof MenuOptions.Type\n\n// UPDATE\n\nconst defaultSide: MenuSide = 'bottom'\nconst defaultAlign: MenuAlign = 'start'\nconst defaultSubmenuSide: MenuSide = 'right'\nconst defaultSubmenuAlign: MenuAlign = 'start'\nconst defaultSideOffset = 0\nconst defaultAlignOffset = 0\nconst defaultCollisionAvoidance = true\nconst defaultCollisionPadding = 0\n\nconst activationKeys = new Set(['Enter', ' '])\nconst searchKeyPattern = /^[\\p{Letter}\\p{Number}]$/u\n\nexport const {\n  FocusPopover: FocusMenu,\n  RestorePopoverFocus: RestoreMenuFocus,\n} = Popover\n\nexport const triggerId = (config: Pick<MenuOptions, 'id' | 'triggerId'>) =>\n  config.triggerId ?? `${config.id}-trigger`\n\nexport const triggerSelector = (\n  config: Pick<MenuOptions, 'id' | 'triggerId' | 'triggerSelector'>,\n) => config.triggerSelector ?? `#${triggerId(config)}`\n\nexport const popupId = (\n  config: Pick<MenuOptions, 'id'>,\n  parentValue?: string | undefined,\n): string =>\n  parentValue === undefined\n    ? `${config.id}-popup`\n    : `${config.id}-submenu-${parentValue}-popup`\n\nexport const positionerId = (\n  config: Pick<MenuOptions, 'id'>,\n  parentValue?: string | undefined,\n): string =>\n  parentValue === undefined\n    ? `${config.id}-positioner`\n    : `${config.id}-submenu-${parentValue}-positioner`\n\nexport const arrowId = (\n  config: Pick<MenuOptions, 'id'>,\n  parentValue?: string | undefined,\n): string =>\n  parentValue === undefined\n    ? `${config.id}-arrow`\n    : `${config.id}-submenu-${parentValue}-arrow`\n\nexport const groupLabelId = (\n  config: Pick<MenuOptions, 'id'>,\n  parentValue?: string | undefined,\n): string =>\n  parentValue === undefined\n    ? `${config.id}-group-label`\n    : `${config.id}-submenu-${parentValue}-group-label`\n\nexport const itemKind = (item: MenuItemDescriptor): MenuItemKind =>\n  item.kind ?? 'item'\n\nexport const itemId = (\n  config: Pick<MenuOptions, 'id'>,\n  item: MenuItemDescriptor,\n): string => item.id ?? `${config.id}-item-${item.value}`\n\nexport const itemFocusSelector = (\n  config: Pick<MenuOptions, 'id'>,\n  item: MenuItemDescriptor,\n): string => `#${itemId(config, item)}`\n\nconst rootAnchorName = (config: Pick<MenuOptions, 'id'>): string =>\n  `--${config.id}-trigger`\n\nconst submenuAnchorName = (\n  config: Pick<MenuOptions, 'id'>,\n  value: string,\n): string => `--${config.id}-item-${value.replaceAll(/[^A-Za-z0-9_-]/gu, '-')}`\n\nexport const itemsForParent = (\n  config: Pick<MenuOptions, 'items'>,\n  parentValue?: string | undefined,\n): ReadonlyArray<MenuItemDescriptor> =>\n  config.items.filter(item => item.parentValue === parentValue)\n\nexport const enabledItems = (\n  config: Pick<MenuOptions, 'isDisabled' | 'items'>,\n  parentValue?: string | undefined,\n): ReadonlyArray<MenuItemDescriptor> =>\n  config.isDisabled === true\n    ? []\n    : itemsForParent(config, parentValue).filter(\n        item => item.isDisabled !== true,\n      )\n\nexport const navigableItems = (\n  config: Pick<MenuOptions, 'isDisabled' | 'items'>,\n  parentValue?: string | undefined,\n): ReadonlyArray<MenuItemDescriptor> =>\n  config.isDisabled === true ? [] : itemsForParent(config, parentValue)\n\nexport const highlightedItem = (\n  config: Pick<MenuOptions, 'highlightedValue' | 'items'>,\n): MenuItemDescriptor | undefined =>\n  config.items.find(item => item.value === config.highlightedValue)\n\nexport const openChange = (\n  open: boolean,\n  reason: MenuOpenChangeReason = 'none',\n  parentValue?: string | undefined,\n): MenuOpenChange => ({ open, reason, parentValue })\n\nexport const highlightChange = (\n  config: Pick<MenuOptions, 'id'>,\n  item: MenuItemDescriptor,\n  reason: MenuHighlightChangeReason = 'none',\n): MenuHighlightChange => ({\n  value: item.value,\n  reason,\n  focusSelector: itemFocusSelector(config, item),\n})\n\nexport const itemPress = (item: MenuItemDescriptor): MenuItemPress => ({\n  value: item.value,\n  kind: itemKind(item),\n})\n\nexport const checkedChange = (item: MenuItemDescriptor): MenuCheckedChange => ({\n  value: item.value,\n  checked: item.isChecked !== true,\n})\n\nexport const radioValueChange = (\n  item: MenuItemDescriptor,\n): MenuRadioValueChange => ({\n  groupValue: item.radioGroupValue ?? 'default',\n  value: item.value,\n})\n\nconst keyboardDirection = (\n  key: string,\n): 'first' | 'last' | 'next' | 'previous' | undefined => {\n  if (key === 'ArrowDown') {\n    return 'next'\n  }\n\n  if (key === 'ArrowUp') {\n    return 'previous'\n  }\n\n  if (key === 'Home') {\n    return 'first'\n  }\n\n  if (key === 'End') {\n    return 'last'\n  }\n\n  return undefined\n}\n\nconst indexOffset = (\n  currentIndex: number,\n  direction: 'next' | 'previous',\n): number => currentIndex + (direction === 'next' ? 1 : -1)\n\nexport const nextHighlightedItem = (\n  config: Pick<MenuOptions, 'highlightedValue' | 'isDisabled' | 'items'>,\n  direction: 'first' | 'last' | 'next' | 'previous',\n  parentValue?: string | undefined,\n): MenuItemDescriptor | undefined => {\n  const items = navigableItems(config, parentValue)\n\n  if (direction === 'first') {\n    return items[0]\n  }\n\n  if (direction === 'last') {\n    return items.at(-1)\n  }\n\n  const currentIndex = items.findIndex(\n    item => item.value === config.highlightedValue,\n  )\n  const resolvedCurrentIndex = currentIndex === -1 ? 0 : currentIndex\n  const candidateIndex = indexOffset(resolvedCurrentIndex, direction)\n\n  if (candidateIndex >= 0 && candidateIndex < items.length) {\n    return items[candidateIndex]\n  }\n\n  return items[resolvedCurrentIndex]\n}\n\nexport const typeaheadItem = (\n  config: Pick<MenuOptions, 'highlightedValue' | 'isDisabled' | 'items'>,\n  search: string,\n  parentValue?: string | undefined,\n): MenuItemDescriptor | undefined => {\n  const items = navigableItems(config, parentValue)\n  const normalizedSearch = search.toLocaleLowerCase()\n  const currentIndex = items.findIndex(\n    item => item.value === config.highlightedValue,\n  )\n  const orderedItems =\n    currentIndex === -1\n      ? items\n      : [...items.slice(currentIndex + 1), ...items.slice(0, currentIndex + 1)]\n\n  return orderedItems.find(item =>\n    (item.textValue ?? item.label)\n      .toLocaleLowerCase()\n      .startsWith(normalizedSearch),\n  )\n}\n\nconst popoverChangeReason = (\n  change: MenuOpenChange,\n): Popover.PopoverChangeReason => {\n  if (change.reason === 'outside-press') {\n    return 'outside-press'\n  }\n\n  if (change.reason === 'escape-key') {\n    return 'escape-key'\n  }\n\n  return change.open ? 'trigger-press' : 'close-press'\n}\n\nexport const commandForOpenChange = (\n  config: Pick<MenuOptions, 'id' | 'triggerId' | 'triggerSelector'>,\n  change: MenuOpenChange,\n): Command.Command<Popover.CommandMessage> =>\n  Popover.commandForOpenChange(\n    {\n      id: config.id,\n      triggerId: triggerId(config),\n      triggerSelector: triggerSelector(config),\n      focusSelector: `#${popupId(config, change.parentValue)}`,\n    },\n    Popover.openChange(change.open, popoverChangeReason(change)),\n  )\n\n// VIEW\n\nexport type MenuPartAttributes<Message> = Readonly<{\n  root: ReadonlyArray<Attribute<Message>>\n  isMounted: boolean\n  isOpen: boolean\n}>\n\nexport type MenuItemAttributes<Message> = Readonly<{\n  item: MenuItemDescriptor\n  root: ReadonlyArray<Attribute<Message>>\n  label: ReadonlyArray<Attribute<Message>>\n  indicator: ReadonlyArray<Attribute<Message>>\n  submenuIndicator: ReadonlyArray<Attribute<Message>>\n}>\n\nexport type MenuPopupAttributes<Message> = Readonly<{\n  parentValue?: string | undefined\n  positioner: MenuPartAttributes<Message>\n  backdrop: MenuPartAttributes<Message>\n  popup: MenuPartAttributes<Message>\n  arrow: MenuPartAttributes<Message>\n  group: ReadonlyArray<Attribute<Message>>\n  groupLabel: ReadonlyArray<Attribute<Message>>\n  separator: ReadonlyArray<Attribute<Message>>\n  items: ReadonlyArray<MenuItemAttributes<Message>>\n  isMounted: boolean\n  isOpen: boolean\n}>\n\nexport type MenuAttributes<Message> = Readonly<{\n  root: ReadonlyArray<Attribute<Message>>\n  trigger: ReadonlyArray<Attribute<Message>>\n  portal: ReadonlyArray<Attribute<Message>>\n  popup: MenuPopupAttributes<Message>\n  submenus: ReadonlyArray<MenuPopupAttributes<Message>>\n  isMounted: boolean\n  isOpen: boolean\n}>\n\nexport type ViewConfig<Message> = MenuOptions &\n  Readonly<{\n    toView: (attributes: MenuAttributes<Message>) => Html\n    onOpenChange?: (change: MenuOpenChange) => Message\n    onHighlightChange?: (change: MenuHighlightChange) => Message\n    onItemPress?: (press: MenuItemPress) => Message\n    onCheckedChange?: (change: MenuCheckedChange) => Message\n    onRadioValueChange?: (change: MenuRadioValueChange) => Message\n    onFocus?: Message\n    onBlur?: Message\n  }>\n\nconst resolvedSide = (\n  config: Pick<MenuOptions, 'side'>,\n  parentValue?: string | undefined,\n): MenuSide =>\n  parentValue === undefined ? (config.side ?? defaultSide) : defaultSubmenuSide\n\nconst resolvedAlign = (\n  config: Pick<MenuOptions, 'align'>,\n  parentValue?: string | undefined,\n): MenuAlign =>\n  parentValue === undefined\n    ? (config.align ?? defaultAlign)\n    : defaultSubmenuAlign\n\nconst mounted = (\n  config: Pick<MenuOptions, 'forceMount' | 'open' | 'transitionStatus'>,\n  isOpen: boolean,\n): boolean =>\n  isOpen ||\n  config.open ||\n  config.forceMount === true ||\n  config.transitionStatus === 'ending'\n\nconst submenuValues = (\n  config: Pick<MenuOptions, 'openSubmenuValues'>,\n): ReadonlyArray<string> => config.openSubmenuValues ?? []\n\nconst isSubmenuOpen = (\n  config: Pick<MenuOptions, 'open' | 'openSubmenuValues'>,\n  parentValue: string,\n): boolean => config.open && submenuValues(config).includes(parentValue)\n\nconst booleanDataAttribute = <Message>(\n  h: ReturnType<typeof html<Message>>,\n  name: string,\n  value: boolean | undefined,\n): ReadonlyArray<Attribute<Message>> =>\n  value === true ? [h.DataAttribute(name, '')] : []\n\nconst optionalBooleanAttribute = <Message>(\n  value: boolean | undefined,\n  toAttribute: (value: boolean) => Attribute<Message>,\n): ReadonlyArray<Attribute<Message>> =>\n  value === true ? [toAttribute(true)] : []\n\nconst optionalMessageAttribute = <Message>(\n  message: Option.Option<Message>,\n  toAttribute: (message: Message) => Attribute<Message>,\n): ReadonlyArray<Attribute<Message>> =>\n  Option.match(message, {\n    onNone: () => [],\n    onSome: value => [toAttribute(value)],\n  })\n\nconst openMessage = <Message>(\n  config: Pick<ViewConfig<Message>, 'onOpenChange'>,\n  change: MenuOpenChange,\n): Option.Option<Message> =>\n  Predicate.isNotUndefined(config.onOpenChange)\n    ? Option.some(config.onOpenChange(change))\n    : Option.none()\n\nconst highlightMessage = <Message>(\n  config: Pick<ViewConfig<Message>, 'id' | 'isDisabled' | 'onHighlightChange'>,\n  item: MenuItemDescriptor,\n  reason: MenuHighlightChangeReason,\n): Option.Option<Message> =>\n  Predicate.isNotUndefined(config.onHighlightChange) &&\n  config.isDisabled !== true &&\n  (item.isDisabled !== true || reason !== 'item-hover')\n    ? Option.some(\n        config.onHighlightChange(highlightChange(config, item, reason)),\n      )\n    : Option.none()\n\nconst itemPressMessage = <Message>(\n  config: Pick<ViewConfig<Message>, 'isDisabled' | 'onItemPress'>,\n  item: MenuItemDescriptor,\n): Option.Option<Message> =>\n  Predicate.isNotUndefined(config.onItemPress) &&\n  config.isDisabled !== true &&\n  item.isDisabled !== true &&\n  itemKind(item) === 'item'\n    ? Option.some(config.onItemPress(itemPress(item)))\n    : Option.none()\n\nconst checkedMessage = <Message>(\n  config: Pick<ViewConfig<Message>, 'isDisabled' | 'onCheckedChange'>,\n  item: MenuItemDescriptor,\n): Option.Option<Message> =>\n  Predicate.isNotUndefined(config.onCheckedChange) &&\n  config.isDisabled !== true &&\n  item.isDisabled !== true &&\n  itemKind(item) === 'checkbox'\n    ? Option.some(config.onCheckedChange(checkedChange(item)))\n    : Option.none()\n\nconst radioMessage = <Message>(\n  config: Pick<ViewConfig<Message>, 'isDisabled' | 'onRadioValueChange'>,\n  item: MenuItemDescriptor,\n): Option.Option<Message> =>\n  Predicate.isNotUndefined(config.onRadioValueChange) &&\n  config.isDisabled !== true &&\n  item.isDisabled !== true &&\n  itemKind(item) === 'radio'\n    ? Option.some(config.onRadioValueChange(radioValueChange(item)))\n    : Option.none()\n\nconst openStateDataAttributes = <Message>(\n  h: ReturnType<typeof html<Message>>,\n  open: boolean,\n): ReadonlyArray<Attribute<Message>> =>\n  open ? [h.DataAttribute('open', '')] : [h.DataAttribute('closed', '')]\n\nconst transitionDataAttributes = <Message>(\n  h: ReturnType<typeof html<Message>>,\n  transitionStatus: MenuTransitionStatus | undefined,\n): ReadonlyArray<Attribute<Message>> => {\n  if (transitionStatus === 'starting') {\n    return [h.DataAttribute('starting-style', '')]\n  }\n\n  if (transitionStatus === 'ending') {\n    return [h.DataAttribute('ending-style', '')]\n  }\n\n  return []\n}\n\nconst placementAttributes = <Message>(\n  h: ReturnType<typeof html<Message>>,\n  config: ViewConfig<Message>,\n  parentValue?: string | undefined,\n): ReadonlyArray<Attribute<Message>> => [\n  h.DataAttribute('side', resolvedSide(config, parentValue)),\n  h.DataAttribute('align', resolvedAlign(config, parentValue)),\n  h.DataAttribute(\n    'side-offset',\n    String(\n      parentValue === undefined ? (config.sideOffset ?? defaultSideOffset) : 0,\n    ),\n  ),\n  h.DataAttribute(\n    'align-offset',\n    String(\n      parentValue === undefined\n        ? (config.alignOffset ?? defaultAlignOffset)\n        : -3,\n    ),\n  ),\n  h.DataAttribute(\n    'collision-avoidance',\n    String(config.collisionAvoidance ?? defaultCollisionAvoidance),\n  ),\n  h.DataAttribute(\n    'collision-padding',\n    String(config.collisionPadding ?? defaultCollisionPadding),\n  ),\n]\n\nconst horizontalAnchorStyle = (\n  config: Pick<MenuOptions, 'align'>,\n  parentValue?: string | undefined,\n): Readonly<Record<string, string>> => {\n  const align = resolvedAlign(config, parentValue)\n\n  if (align === 'center') {\n    return { left: 'anchor(center)', translate: '-50% 0' }\n  }\n\n  if (align === 'end') {\n    return { left: 'anchor(right)', translate: '-100% 0' }\n  }\n\n  return { left: 'anchor(left)' }\n}\n\nconst verticalAnchorStyle = (\n  config: Pick<MenuOptions, 'align'>,\n  parentValue?: string | undefined,\n): Readonly<Record<string, string>> => {\n  const align = resolvedAlign(config, parentValue)\n\n  if (align === 'center') {\n    return { top: 'anchor(center)', translate: '0 -50%' }\n  }\n\n  if (align === 'end') {\n    return { top: 'anchor(bottom)', translate: '0 -100%' }\n  }\n\n  return { top: 'anchor(top)' }\n}\n\nconst sideOffset = (\n  config: Pick<MenuOptions, 'sideOffset'>,\n  parentValue?: string | undefined,\n): number =>\n  parentValue === undefined ? (config.sideOffset ?? defaultSideOffset) : 0\n\nconst placementStyle = (\n  config: Pick<MenuOptions, 'align' | 'side' | 'sideOffset'>,\n  parentValue?: string | undefined,\n): Readonly<Record<string, string>> => {\n  const offset = `${sideOffset(config, parentValue)}px`\n  const side = resolvedSide(config, parentValue)\n\n  if (side === 'top') {\n    return {\n      ...horizontalAnchorStyle(config, parentValue),\n      bottom: `calc(anchor(top) + ${offset})`,\n    }\n  }\n\n  if (side === 'left' || side === 'inline-start') {\n    return {\n      ...verticalAnchorStyle(config, parentValue),\n      right: `calc(anchor(left) + ${offset})`,\n    }\n  }\n\n  if (side === 'right' || side === 'inline-end') {\n    return {\n      ...verticalAnchorStyle(config, parentValue),\n      left: `calc(anchor(right) + ${offset})`,\n    }\n  }\n\n  return {\n    ...horizontalAnchorStyle(config, parentValue),\n    top: `calc(anchor(bottom) + ${offset})`,\n  }\n}\n\nconst popupAnchorName = (\n  config: Pick<MenuOptions, 'id'>,\n  parentValue?: string | undefined,\n): string =>\n  parentValue === undefined\n    ? rootAnchorName(config)\n    : submenuAnchorName(config, parentValue)\n\nconst rootAttributes = <Message>(\n  h: ReturnType<typeof html<Message>>,\n  config: ViewConfig<Message>,\n): ReadonlyArray<Attribute<Message>> => [\n  h.DataAttribute('side', resolvedSide(config)),\n  h.DataAttribute('align', resolvedAlign(config)),\n  ...booleanDataAttribute(h, 'disabled', config.isDisabled),\n]\n\nconst triggerKeyboardMessage = <Message>(\n  config: ViewConfig<Message>,\n  key: string,\n  modifiers: KeyboardModifiers,\n): Option.Option<Message> => {\n  if (modifiers.shiftKey || config.isDisabled === true) {\n    return Option.none()\n  }\n\n  if (activationKeys.has(key) || key === 'ArrowDown' || key === 'ArrowUp') {\n    return openMessage(config, openChange(true, 'keyboard-open'))\n  }\n\n  return Option.none()\n}\n\nconst triggerAttributes = <Message>(\n  h: ReturnType<typeof html<Message>>,\n  config: ViewConfig<Message>,\n): ReadonlyArray<Attribute<Message>> => [\n  h.Id(triggerId(config)),\n  h.Type('button'),\n  h.AriaHasPopup('menu'),\n  h.AriaExpanded(config.open),\n  h.AriaControls(popupId(config)),\n  h.Style({ anchorName: rootAnchorName(config) }),\n  ...booleanDataAttribute(h, 'disabled', config.isDisabled),\n  ...(config.open ? [h.DataAttribute('popup-open', '')] : []),\n  ...optionalBooleanAttribute<Message>(config.isDisabled, value =>\n    h.AriaDisabled(value),\n  ),\n  ...optionalMessageAttribute(\n    config.isDisabled === true\n      ? Option.none()\n      : openMessage(config, openChange(!config.open, 'trigger-press')),\n    message => h.OnClick(message),\n  ),\n  h.OnKeyDownPreventDefault((key, modifiers) =>\n    triggerKeyboardMessage(config, key, modifiers),\n  ),\n  ...(Predicate.isNotUndefined(config.onFocus)\n    ? [h.OnFocus(config.onFocus)]\n    : []),\n  ...(Predicate.isNotUndefined(config.onBlur) ? [h.OnBlur(config.onBlur)] : []),\n]\n\nconst portalAttributes = <Message>(\n  h: ReturnType<typeof html<Message>>,\n): ReadonlyArray<Attribute<Message>> => [h.DataAttribute('portal', '')]\n\nconst positionerAttributes = <Message>(\n  h: ReturnType<typeof html<Message>>,\n  config: ViewConfig<Message>,\n  isOpen: boolean,\n  isMounted: boolean,\n  parentValue?: string | undefined,\n): MenuPartAttributes<Message> => ({\n  root: isMounted\n    ? [\n        h.Id(positionerId(config, parentValue)),\n        ...(isOpen ? [] : [h.Hidden(true)]),\n        ...openStateDataAttributes(h, isOpen),\n        ...placementAttributes(h, config, parentValue),\n        h.Style({\n          position: 'absolute',\n          positionAnchor: popupAnchorName(config, parentValue),\n          inset: 'auto',\n          margin: '0',\n          ...placementStyle(config, parentValue),\n        }),\n      ]\n    : [],\n  isMounted,\n  isOpen,\n})\n\nconst backdropAttributes = <Message>(\n  h: ReturnType<typeof html<Message>>,\n  config: ViewConfig<Message>,\n  isOpen: boolean,\n  isMounted: boolean,\n  parentValue?: string | undefined,\n): MenuPartAttributes<Message> => ({\n  root: isMounted\n    ? [\n        h.Role('presentation'),\n        ...(isOpen ? [] : [h.Hidden(true)]),\n        ...openStateDataAttributes(h, isOpen),\n        ...transitionDataAttributes(h, config.transitionStatus),\n        h.Style({\n          position: 'fixed',\n          inset: '0',\n          zIndex: '49',\n        }),\n        ...optionalMessageAttribute(\n          openMessage(config, openChange(false, 'outside-press', parentValue)),\n          message => h.OnClick(message),\n        ),\n        ...optionalMessageAttribute(\n          openMessage(config, openChange(false, 'outside-press', parentValue)),\n          message => h.OnContextMenu(message),\n        ),\n      ]\n    : [],\n  isMounted,\n  isOpen,\n})\n\nconst popupKeyboardMessage = <Message>(\n  config: ViewConfig<Message>,\n  key: string,\n  modifiers: KeyboardModifiers,\n  parentValue?: string | undefined,\n): Option.Option<Message> => {\n  if (modifiers.shiftKey) {\n    return Option.none()\n  }\n\n  if (key === 'Escape') {\n    return openMessage(config, openChange(false, 'escape-key', parentValue))\n  }\n\n  if (key === 'ArrowLeft' && parentValue !== undefined) {\n    return openMessage(config, openChange(false, 'submenu-close', parentValue))\n  }\n\n  if (key === 'ArrowRight') {\n    const item = highlightedItem(config)\n\n    if (item !== undefined && itemKind(item) === 'submenu-trigger') {\n      return openMessage(config, openChange(true, 'submenu-open', item.value))\n    }\n  }\n\n  const direction = keyboardDirection(key)\n\n  if (direction !== undefined) {\n    const item = nextHighlightedItem(config, direction, parentValue)\n\n    return item === undefined\n      ? Option.none()\n      : highlightMessage(config, item, 'keyboard-navigation')\n  }\n\n  if (searchKeyPattern.test(key)) {\n    const item = typeaheadItem(config, key, parentValue)\n\n    return item === undefined\n      ? Option.none()\n      : highlightMessage(config, item, 'typeahead')\n  }\n\n  return Option.none()\n}\n\nconst popupAttributes = <Message>(\n  h: ReturnType<typeof html<Message>>,\n  config: ViewConfig<Message>,\n  isOpen: boolean,\n  isMounted: boolean,\n  parentValue?: string | undefined,\n): MenuPartAttributes<Message> => ({\n  root: isMounted\n    ? [\n        h.Id(popupId(config, parentValue)),\n        h.Popover('manual'),\n        h.Role('menu'),\n        h.Tabindex(-1),\n        ...(isOpen ? [] : [h.Hidden(true)]),\n        ...openStateDataAttributes(h, isOpen),\n        ...transitionDataAttributes(h, config.transitionStatus),\n        ...placementAttributes(h, config, parentValue),\n        h.Style({\n          position: 'absolute',\n          positionAnchor: popupAnchorName(config, parentValue),\n          inset: 'auto',\n          margin: '0',\n          ...placementStyle(config, parentValue),\n        }),\n        ...optionalMessageAttribute(\n          openMessage(config, openChange(isOpen, 'none', parentValue)),\n          message => h.OnContextMenu(message),\n        ),\n        h.OnKeyDownPreventDefault((key, modifiers) =>\n          popupKeyboardMessage(config, key, modifiers, parentValue),\n        ),\n      ]\n    : [],\n  isMounted,\n  isOpen,\n})\n\nconst positionedPartAttributes = <Message>(\n  h: ReturnType<typeof html<Message>>,\n  config: ViewConfig<Message>,\n  isOpen: boolean,\n  isMounted: boolean,\n  id: string,\n  parentValue?: string | undefined,\n): MenuPartAttributes<Message> => ({\n  root: isMounted\n    ? [\n        h.Id(id),\n        ...(isOpen ? [] : [h.Hidden(true)]),\n        ...openStateDataAttributes(h, isOpen),\n        ...placementAttributes(h, config, parentValue),\n      ]\n    : [],\n  isMounted,\n  isOpen,\n})\n\nconst itemRole = (item: MenuItemDescriptor): string => {\n  const kind = itemKind(item)\n\n  if (kind === 'checkbox') {\n    return 'menuitemcheckbox'\n  }\n\n  if (kind === 'radio') {\n    return 'menuitemradio'\n  }\n\n  return 'menuitem'\n}\n\nconst itemStateDataAttributes = <Message>(\n  h: ReturnType<typeof html<Message>>,\n  config: ViewConfig<Message>,\n  item: MenuItemDescriptor,\n): ReadonlyArray<Attribute<Message>> => [\n  ...(config.highlightedValue === item.value\n    ? [h.DataAttribute('highlighted', '')]\n    : []),\n  ...booleanDataAttribute(h, 'disabled', item.isDisabled),\n  ...(itemKind(item) === 'checkbox' || itemKind(item) === 'radio'\n    ? [\n        item.isChecked === true\n          ? h.DataAttribute('checked', '')\n          : h.DataAttribute('unchecked', ''),\n      ]\n    : []),\n  ...(itemKind(item) === 'submenu-trigger' && isSubmenuOpen(config, item.value)\n    ? [h.DataAttribute('popup-open', ''), h.DataAttribute('open', '')]\n    : []),\n]\n\nconst itemClickMessage = <Message>(\n  config: ViewConfig<Message>,\n  item: MenuItemDescriptor,\n): Option.Option<Message> => {\n  if (config.isDisabled === true || item.isDisabled === true) {\n    return Option.none()\n  }\n\n  if (itemKind(item) === 'checkbox') {\n    return checkedMessage(config, item)\n  }\n\n  if (itemKind(item) === 'radio') {\n    return radioMessage(config, item)\n  }\n\n  if (itemKind(item) === 'submenu-trigger') {\n    return openMessage(config, openChange(true, 'submenu-open', item.value))\n  }\n\n  return itemPressMessage(config, item)\n}\n\nconst itemAttributes = <Message>(\n  h: ReturnType<typeof html<Message>>,\n  config: ViewConfig<Message>,\n  item: MenuItemDescriptor,\n): ReadonlyArray<Attribute<Message>> => [\n  h.Id(itemId(config, item)),\n  h.Role(itemRole(item)),\n  h.Tabindex(config.open && config.highlightedValue === item.value ? 0 : -1),\n  ...(itemKind(item) === 'checkbox' || itemKind(item) === 'radio'\n    ? [h.AriaChecked(item.isChecked === true)]\n    : []),\n  ...(itemKind(item) === 'submenu-trigger'\n    ? [\n        h.AriaHasPopup('menu'),\n        h.AriaExpanded(isSubmenuOpen(config, item.value)),\n        h.AriaControls(popupId(config, item.value)),\n        h.Style({ anchorName: submenuAnchorName(config, item.value) }),\n      ]\n    : []),\n  ...optionalBooleanAttribute<Message>(item.isDisabled, value =>\n    h.AriaDisabled(value),\n  ),\n  ...itemStateDataAttributes(h, config, item),\n  ...optionalMessageAttribute(itemClickMessage(config, item), message =>\n    h.OnClick(message),\n  ),\n  ...optionalMessageAttribute(\n    itemKind(item) === 'submenu-trigger'\n      ? openMessage(config, openChange(true, 'submenu-open', item.value))\n      : highlightMessage(config, item, 'item-hover'),\n    message => h.OnMouseEnter(message),\n  ),\n  ...optionalMessageAttribute(itemClickMessage(config, item), message =>\n    h.OnKeyDownPreventDefault(key =>\n      activationKeys.has(key) ? Option.some(message) : Option.none(),\n    ),\n  ),\n]\n\nconst itemLabelAttributes = <Message>(\n  h: ReturnType<typeof html<Message>>,\n  config: ViewConfig<Message>,\n  item: MenuItemDescriptor,\n): ReadonlyArray<Attribute<Message>> => itemStateDataAttributes(h, config, item)\n\nconst itemIndicatorAttributes = <Message>(\n  h: ReturnType<typeof html<Message>>,\n  config: ViewConfig<Message>,\n  item: MenuItemDescriptor,\n): ReadonlyArray<Attribute<Message>> =>\n  itemKind(item) === 'checkbox' || itemKind(item) === 'radio'\n    ? itemStateDataAttributes(h, config, item)\n    : []\n\nconst submenuIndicatorAttributes = <Message>(\n  h: ReturnType<typeof html<Message>>,\n  config: ViewConfig<Message>,\n  item: MenuItemDescriptor,\n): ReadonlyArray<Attribute<Message>> =>\n  itemKind(item) === 'submenu-trigger'\n    ? itemStateDataAttributes(h, config, item)\n    : []\n\nconst menuItems = <Message>(\n  h: ReturnType<typeof html<Message>>,\n  config: ViewConfig<Message>,\n  parentValue?: string | undefined,\n): ReadonlyArray<MenuItemAttributes<Message>> =>\n  itemsForParent(config, parentValue).map(item => ({\n    item,\n    root: itemAttributes(h, config, item),\n    label: itemLabelAttributes(h, config, item),\n    indicator: itemIndicatorAttributes(h, config, item),\n    submenuIndicator: submenuIndicatorAttributes(h, config, item),\n  }))\n\nconst popupParts = <Message>(\n  h: ReturnType<typeof html<Message>>,\n  config: ViewConfig<Message>,\n  parentValue?: string | undefined,\n): MenuPopupAttributes<Message> => {\n  const isOpen =\n    parentValue === undefined ? config.open : isSubmenuOpen(config, parentValue)\n  const isMounted = mounted(config, isOpen)\n\n  return {\n    parentValue,\n    positioner: positionerAttributes(h, config, isOpen, isMounted, parentValue),\n    backdrop: backdropAttributes(h, config, isOpen, isMounted, parentValue),\n    popup: popupAttributes(h, config, isOpen, isMounted, parentValue),\n    arrow: positionedPartAttributes(\n      h,\n      config,\n      isOpen,\n      isMounted,\n      arrowId(config, parentValue),\n      parentValue,\n    ),\n    group: isMounted ? [h.Role('group')] : [],\n    groupLabel: isMounted ? [h.Id(groupLabelId(config, parentValue))] : [],\n    separator: isMounted\n      ? [h.Role('separator'), h.AriaOrientation('horizontal')]\n      : [],\n    items: menuItems(h, config, parentValue),\n    isMounted,\n    isOpen,\n  }\n}\n\nexport const view = <Message>(config: ViewConfig<Message>): Html => {\n  const h = html<Message>()\n  const submenus = config.items\n    .filter(item => itemKind(item) === 'submenu-trigger')\n    .map(item => popupParts(h, config, item.value))\n\n  return config.toView({\n    root: rootAttributes(h, config),\n    trigger: triggerAttributes(h, config),\n    portal: portalAttributes(h),\n    popup: popupParts(h, config),\n    submenus,\n    isMounted: mounted(config, config.open),\n    isOpen: config.open,\n  })\n}\n"
    }
  ],
  "originProvenance": [
    {
      "originKind": "base-ui",
      "originName": "Base UI Menu",
      "docsUrl": "https://base-ui.com/react/components/menu",
      "sourceUrl": "https://github.com/mui/base-ui/tree/ea3818dec91923d4287b38be21322d2e5068d347/packages/react/src/menu",
      "localRepoPath": "repos/base-ui",
      "gitRef": "ea3818dec91923d4287b38be21322d2e5068d347",
      "inventoryHash": "ea3818dec91923d4287b38be21322d2e5068d347",
      "sourcePaths": [
        "repos/base-ui/packages/react/src/menu/index.ts",
        "repos/base-ui/packages/react/src/menu/root/MenuRoot.tsx",
        "repos/base-ui/packages/react/src/menu/trigger/MenuTrigger.tsx",
        "repos/base-ui/packages/react/src/menu/popup/MenuPopup.tsx",
        "repos/base-ui/packages/react/src/menu/positioner/MenuPositioner.tsx",
        "repos/base-ui/packages/react/src/menu/item/MenuItem.tsx",
        "repos/base-ui/packages/react/src/menu/checkbox-item/MenuCheckboxItem.tsx",
        "repos/base-ui/packages/react/src/menu/radio-item/MenuRadioItem.tsx",
        "repos/base-ui/packages/react/src/menu/submenu-root/MenuSubmenuRoot.tsx",
        "repos/base-ui/packages/react/src/menu/submenu-trigger/MenuSubmenuTrigger.tsx"
      ],
      "docsPaths": [
        "repos/base-ui/docs/src/app/(docs)/react/components/menu/page.mdx",
        "repos/base-ui/docs/src/app/(docs)/react/components/menu/types.md",
        "repos/base-ui/docs/src/app/(docs)/react/components/menu/types.ts"
      ],
      "examplePaths": [
        "repos/base-ui/docs/src/app/(docs)/react/components/menu/demos/hero/css-modules/index.tsx",
        "repos/base-ui/docs/src/app/(docs)/react/components/menu/demos/checkbox-items/css-modules/index.tsx",
        "repos/base-ui/docs/src/app/(docs)/react/components/menu/demos/radio-items/css-modules/index.tsx",
        "repos/base-ui/docs/src/app/(docs)/react/components/menu/demos/submenu/css-modules/index.tsx"
      ],
      "testPaths": [
        "repos/base-ui/packages/react/src/menu/root/MenuRoot.test.tsx",
        "repos/base-ui/packages/react/src/menu/item/MenuItem.test.tsx",
        "repos/base-ui/packages/react/src/menu/checkbox-item/MenuCheckboxItem.test.tsx",
        "repos/base-ui/packages/react/src/menu/radio-item/MenuRadioItem.test.tsx",
        "repos/base-ui/packages/react/src/menu/submenu-trigger/MenuSubmenuTrigger.test.tsx",
        "repos/base-ui/packages/react/src/menu/positioner/MenuPositioner.spec.tsx"
      ]
    }
  ],
  "dependencies": {
    "registry": [
      {
        "specifier": "base-ui/popover",
        "classification": "registry-local",
        "target": "base-ui/popover",
        "reason": "Menu reuses the local Popover focus command and deterministic placement conventions without creating another overlay stack."
      }
    ],
    "runtime": [
      {
        "specifier": "foldkit",
        "classification": "allowed-runtime",
        "target": "npm:foldkit",
        "reason": "Provides Html, Attribute, Command, and keyboard event helpers for the Foldkit-native primitive."
      },
      {
        "specifier": "effect",
        "classification": "allowed-runtime",
        "target": "npm:effect",
        "reason": "Provides Effect Schema, Option, and predicate helpers for serializable options and event payloads."
      }
    ],
    "development": [
      {
        "specifier": "@base-ui-components/react/menu",
        "classification": "replace-with-foldkit",
        "target": "base-ui/menu",
        "reason": "Origin Base UI React Menu primitive is replaced by this Foldkit implementation."
      },
      {
        "specifier": "@base-ui/react/menu",
        "classification": "replace-with-foldkit",
        "target": "base-ui/menu",
        "reason": "Origin Base UI React Menu primitive is replaced by this Foldkit implementation."
      },
      {
        "specifier": "react",
        "classification": "dev-or-fixture-only",
        "target": "",
        "reason": "React is origin fixture evidence only, not installable Foldkit source."
      }
    ]
  },
  "examples": [],
  "quality": {
    "availability": "installable",
    "implementationStatus": "implemented",
    "parityStatus": "accepted",
    "driftStatus": "current",
    "deviations": [
      {
        "id": "base-ui-menu-model-owned-state",
        "summary": "Open, highlighted, submenu, checkbox, and radio state are model-owned inputs and interactions emit typed facts instead of mutating internal component state.",
        "required": true,
        "status": "accepted",
        "rationale": "Foldkit preserves unidirectional data flow and keeps menu state in the consuming model."
      },
      {
        "id": "base-ui-menu-command-facing-focus-effects",
        "summary": "Focus handoff and restoration reuse the Popover command-facing helpers instead of hiding side effects inside render helpers.",
        "required": true,
        "status": "accepted",
        "rationale": "Menu side effects must stay at Foldkit's Command boundary. The installable view remains pure and deterministic."
      },
      {
        "id": "base-ui-menu-deterministic-placement-attributes",
        "summary": "Placement is represented through deterministic side, align, offset, collision, positioner, popup, and submenu attributes without DOM measurement or collision flipping.",
        "required": true,
        "status": "accepted",
        "rationale": "Measured collision behavior belongs behind a shared measurement service, not an ad hoc Menu render helper side effect."
      }
    ]
  }
}
